zue/__init__.py
zue-0.1.1.dist-info/METADATA
zue-0.1.1.dist-info/WHEEL
zue-0.1.1.dist-info/RECORD
