Metadata-Version: 2.4
Name: zue
Version: 0.1.1
Summary: Zue AI
Project-URL: Homepage, https://github.com/zueai
Author-email: Zue AI <a@zue.ai>
Classifier: License :: OSI Approved :: MIT License
Classifier: Operating System :: OS Independent
Classifier: Programming Language :: Python :: 3
Requires-Python: >=3.7
